agentsphere/__init__.py
agentsphere/api/__init__.py
agentsphere/api/client/__init__.py
agentsphere/api/client/api/__init__.py
agentsphere/api/client/api/sandboxes/__init__.py
agentsphere/api/client/api/sandboxes/delete_sandboxes_sandbox_id.py
agentsphere/api/client/api/sandboxes/get_sandboxes.py
agentsphere/api/client/api/sandboxes/get_sandboxes_metrics.py
agentsphere/api/client/api/sandboxes/get_sandboxes_sandbox_id.py
agentsphere/api/client/api/sandboxes/get_sandboxes_sandbox_id_logs.py
agentsphere/api/client/api/sandboxes/get_sandboxes_sandbox_id_metrics.py
agentsphere/api/client/api/sandboxes/get_v2_sandboxes.py
agentsphere/api/client/api/sandboxes/post_sandboxes.py
agentsphere/api/client/api/sandboxes/post_sandboxes_sandbox_id_pause.py
agentsphere/api/client/api/sandboxes/post_sandboxes_sandbox_id_refreshes.py
agentsphere/api/client/api/sandboxes/post_sandboxes_sandbox_id_resume.py
agentsphere/api/client/api/sandboxes/post_sandboxes_sandbox_id_timeout.py
agentsphere/api/client/api/templates/__init__.py
agentsphere/api/client/api/templates/delete_templates_template_id.py
agentsphere/api/client/api/templates/get_templates.py
agentsphere/api/client/api/templates/get_templates_template_id_builds_build_id_status.py
agentsphere/api/client/api/templates/get_templates_template_id_files_hash.py
agentsphere/api/client/api/templates/patch_templates_template_id.py
agentsphere/api/client/api/templates/post_templates.py
agentsphere/api/client/api/templates/post_templates_template_id.py
agentsphere/api/client/api/templates/post_templates_template_id_builds_build_id.py
agentsphere/api/client/api/templates/post_v2_templates.py
agentsphere/api/client/api/templates/post_v_2_templates_template_id_builds_build_id.py
agentsphere/api/client/client.py
agentsphere/api/client/errors.py
agentsphere/api/client/models/__init__.py
agentsphere/api/client/models/aws_registry.py
agentsphere/api/client/models/aws_registry_type.py
agentsphere/api/client/models/build_log_entry.py
agentsphere-2.1.6.dist-info/METADATA
agentsphere-2.1.6.dist-info/WHEEL
agentsphere-2.1.6.dist-info/licenses/LICENSE
agentsphere-2.1.6.dist-info/RECORD
